sid_lib_work_login/__init__.py
sid_lib_work_login/__main__.py
sid_lib_work_login/sub_dir/__init__.py
sid_lib_work_login/sub_dir/work_login.py
sid_lib_work_login-0.1.3.dist-info/LICENSE
sid_lib_work_login-0.1.3.dist-info/METADATA
sid_lib_work_login-0.1.3.dist-info/WHEEL
sid_lib_work_login-0.1.3.dist-info/entry_points.txt
sid_lib_work_login-0.1.3.dist-info/top_level.txt
sid_lib_work_login-0.1.3.dist-info/RECORD
